{
    "sources": [
        {
            "name": "Amazon DocumentDB(Read)",
            "category": "Storage Sink",
            "patterns": [
                "(?i).*(aws_cdk.*aws_docdb).*",
                "(?i).*boto.*(?:find.{0,1}one).*"
            ],
            "tags": {
                "id": "Storages.AmazonDocumentDB.Read",
                "language": "python",
                "technology": "documentdb",
                "type": "Database"
            }
        },
        {
            "name": "Amazon DocumentDB(Write)",
            "category": "Storage Sink",
            "patterns": [
                "(?i).*boto.*(?:insert.{0,1}(?:one|many)).*"
            ],
            "tags": {
                "id": "Storages.AmazonDocumentDB.Write",
                "language": "python",
                "technology": "documentdb",
                "type": "Database"
            }
        }
    ]
}